{
  "timestamp": "2026-03-28T21:16:36.448022Z",
  "current_node": "run_tests",
  "completed_nodes": [
    "start",
    "run_tests"
  ],
  "node_retries": {},
  "context_values": {
    "internal.fidelity": "compact",
    "internal.node_visit_count": 1,
    "thread.start.current_node": "run_tests",
    "current.preamble": "Goal: Run tests and report results\n",
    "internal.retry_count.start": 0,
    "internal.thread_id": "start",
    "failure_class": "",
    "internal.work_dir": "/var/folders/nm/bd2dwzy52t1ckn3tklsfmy1c0000gn/T/.tmpnOPw0i/fabro-data/runs/20260328-dry-run-01KMV4WM8MFAHN9E21K0QPCMBJ/worktree",
    "internal.run_id": "01KMV4WM8MFAHN9E21K0QPCMBJ",
    "failure_signature": "",
    "last_response": "[Simulated] Response for stage: run_tests",
    "graph.rankdir": "LR",
    "last_stage": "run_tests",
    "outcome": "success",
    "graph.goal": "Run tests and report results",
    "current_node": "run_tests",
    "internal.retry_count.run_tests": 0,
    "response.run_tests": "[Simulated] Response for stage: run_tests"
  },
  "node_outcomes": {
    "start": {
      "status": "success",
      "notes": "[Simulated] start",
      "usage": null
    },
    "run_tests": {
      "status": "success",
      "context_updates": {
        "response.run_tests": "[Simulated] Response for stage: run_tests",
        "last_stage": "run_tests",
        "last_response": "[Simulated] Response for stage: run_tests"
      },
      "notes": "[Simulated] run_tests",
      "usage": null
    }
  },
  "next_node_id": "report",
  "node_visits": {
    "start": 1,
    "run_tests": 1
  }
}